pantalon/.DS_Store
pantalon/__init__.py
pantalon-1.0.0.dist-info/METADATA
pantalon-1.0.0.dist-info/WHEEL
pantalon-1.0.0.dist-info/RECORD
